{
    "hero": {
        "badge": "தினசரி செய்தி & இதழ்",
        "title": "திராவிட தலைமுறை",
        "subtitle": "சிந்திக்கும் இளம் குரல் | சமத்துவத்தின் பாதை",
        "description": "சாதி, மதம், பாலினம் என எந்த வேறுபாடுமின்றி மனிதன் மனிதனாக வாழ வேண்டிய உரிமையை உரக்க பேசும் இளம் தலைமுறையின் குரல்தான் திராவிட தலைமுறை.",
        "bullet1": "சிந்தனை எங்கள் ஆயுதம்",
        "bullet2": "சமத்துவமே எங்கள் அடையாளம்",
        "read_now": "படிக்க",
        "scroll": "மேலும் அறிய"
    },
    "nav": {
        "home": "முகப்பு",
        "politics": "அரசியல்",
        "education": "கல்வி"
    }
}